cnsp/__init__.py
cnsp-0.0.3.dist-info/LICENSE
cnsp-0.0.3.dist-info/METADATA
cnsp-0.0.3.dist-info/WHEEL
cnsp-0.0.3.dist-info/top_level.txt
cnsp-0.0.3.dist-info/RECORD
