Metadata-Version: 2.1
Name: cnsp
Version: 0.0.3
Summary: Search predictions in mainland China
Home-page: https://github.com/wangxinhe2006/cnsp
Author: 汪心禾
Author-email: wangxinhe06@gmail.com
License: UNKNOWN
Platform: UNKNOWN
Classifier: Programming Language :: Python :: 3
Classifier: Programming Language :: Python :: 3.6
Classifier: Programming Language :: Python :: 3.7
Classifier: Programming Language :: Python :: 3.8
Classifier: Programming Language :: Python :: 3.9
Classifier: License :: OSI Approved :: MIT License
Classifier: Operating System :: OS Independent
Requires-Python: >=3.6
